openstax_accounts/__init__.py
openstax_accounts/apps.py
openstax_accounts/functions.py
openstax_accounts/strategy_2.py
openstax_accounts/tests.py
django_openstax_accounts-1.0.dist-info/LICENSE
django_openstax_accounts-1.0.dist-info/METADATA
django_openstax_accounts-1.0.dist-info/WHEEL
django_openstax_accounts-1.0.dist-info/top_level.txt
django_openstax_accounts-1.0.dist-info/RECORD
