Metadata-Version: 2.1
Name: django-openstax-accounts
Version: 1.0
Summary: A Django app to read data from the logged-in user OpenStax account using the SSO cookie.
Home-page: https://www.openstax.org/
Author: Michael Volo
Author-email: volo@rice.edu
License: GNU Affero General Public License v3
Classifier: Environment :: Web Environment
Classifier: Framework :: Django
Classifier: Framework :: Django :: 3.0
Classifier: Intended Audience :: Developers
Classifier: License :: OSI Approved :: BSD License
Classifier: Operating System :: OS Independent
Classifier: Programming Language :: Python
Classifier: Programming Language :: Python :: 3
Classifier: Programming Language :: Python :: 3 :: Only
Classifier: Programming Language :: Python :: 3.8
Classifier: Programming Language :: Python :: 3.9
Classifier: Programming Language :: Python :: 3.10
Classifier: Programming Language :: Python :: 3.11
Classifier: Programming Language :: Python :: 3.12
Classifier: Topic :: Internet :: WWW/HTTP
Classifier: Topic :: Internet :: WWW/HTTP :: Dynamic Content
Requires-Python: >=3.8
License-File: LICENSE
Requires-Dist: Django >=3.0
Requires-Dist: PyJWE
Requires-Dist: PyJWT
Requires-Dist: requests-oauthlib
